japper/__init__.py
japper/app_config.py
japper/app_main_view.py
japper/appmode.html
japper/debug.py
japper/global.html
japper/japper_app_main.py
japper/japper_events.py
japper/page.py
japper/page_controller.py
japper/page_view.py
japper/style.py
japper/style_old.py
japper/utils.py
japper/vue_widget_logger.py
japper/widget_wrapper.py
japper/__pycache__/__init__.cpython-311.pyc
japper/__pycache__/__init__.cpython-39.pyc
japper/__pycache__/app_config.cpython-312.pyc
japper/__pycache__/app_main_view.cpython-311.pyc
japper/__pycache__/app_main_view.cpython-39.pyc
japper/__pycache__/debug.cpython-311.pyc
japper/__pycache__/debug.cpython-39.pyc
japper/__pycache__/japper_app_main.cpython-311.pyc
japper/__pycache__/japper_app_main.cpython-39.pyc
japper/__pycache__/japper_events.cpython-311.pyc
japper/__pycache__/page.cpython-311.pyc
japper/__pycache__/page.cpython-39.pyc
japper/__pycache__/page_controller.cpython-311.pyc
japper/__pycache__/page_view.cpython-311.pyc
japper/__pycache__/style.cpython-311.pyc
japper/__pycache__/style.cpython-312.pyc
japper/__pycache__/utils.cpython-311.pyc
japper/__pycache__/utils.cpython-312.pyc
japper/__pycache__/utils.cpython-39.pyc
japper/__pycache__/vue_widget_logger.cpython-311.pyc
japper/__pycache__/vue_widget_logger.cpython-39.pyc
japper/__pycache__/widget_wrapper.cpython-311.pyc
japper/widgets/__init__.py
japper/widgets/fileupload.py
japper/widgets/fileupload.vue
japper/widgets/loading_dialog.py
japper/widgets/navigation_menu.py
japper/widgets/popup_alert.py
japper/widgets/toast_alert.py
japper/widgets/__pycache__/__init__.cpython-311.pyc
japper/widgets/__pycache__/__init__.cpython-39.pyc
japper/widgets/__pycache__/fileupload.cpython-311.pyc
japper/widgets/__pycache__/fileupload.cpython-39.pyc
japper/widgets/__pycache__/loading_dialog.cpython-311.pyc
japper/widgets/__pycache__/loading_dialog.cpython-39.pyc
japper/widgets/__pycache__/navigation_menu.cpython-311.pyc
japper/widgets/__pycache__/navigation_menu.cpython-39.pyc
japper-0.0.25.dist-info/METADATA
japper-0.0.25.dist-info/WHEEL
japper-0.0.25.dist-info/entry_points.txt
japper-0.0.25.dist-info/top_level.txt
japper-0.0.25.dist-info/RECORD
