Metadata-Version: 2.1
Name: japper
Version: 0.0.25
Summary: Japper
Author-email: "Kim, I Luk" <yirugi@gmail.com>
License: MIT License
Keywords: japper,Jupyter,ipyvuetify,voila
Classifier: Development Status :: 2 - Pre-Alpha
Classifier: Programming Language :: Python
Requires-Python: >=3.9
Requires-Dist: setuptools
Requires-Dist: pdoc3
Requires-Dist: ipyvuetify
Requires-Dist: ipywidgets
Requires-Dist: ipykernel
Requires-Dist: voila
Requires-Dist: jupyterlab
Requires-Dist: jinja2
Requires-Dist: rich-click
Requires-Dist: rich
Requires-Dist: pydantic
Provides-Extra: runtime
Requires-Dist: voila ; extra == 'runtime'
